esmf_git.py
esmf_git-0.6.0.dist-info/LICENSE
esmf_git-0.6.0.dist-info/METADATA
esmf_git-0.6.0.dist-info/WHEEL
esmf_git-0.6.0.dist-info/top_level.txt
esmf_git-0.6.0.dist-info/RECORD
