Metadata-Version: 2.1
Name: esmf-git
Version: 0.6.0
Summary: Standard Git Library for ESMF applications.
Home-page: UNKNOWN
Author: Ryan Long
Author-email: ryan.long@noaa.gov
License: MIT
Platform: UNKNOWN
Classifier: Programming Language :: Python
Classifier: Programming Language :: Python :: 3
Classifier: Programming Language :: Python :: 3.5
Classifier: Programming Language :: Python :: 3.6
License-File: LICENSE
